inwxcli/__init__.py
inwxcli/inwx.py
inwxcli/inwxcli.py
inwxcli-1.1.dist-info/DESCRIPTION.rst
inwxcli-1.1.dist-info/METADATA
inwxcli-1.1.dist-info/RECORD
inwxcli-1.1.dist-info/WHEEL
inwxcli-1.1.dist-info/entry_points.txt
inwxcli-1.1.dist-info/metadata.json
inwxcli-1.1.dist-info/top_level.txt
