Metadata-Version: 2.0
Name: inwxcli
Version: 1.1
Summary: Command line interface for inwx.com.
Home-page: https://github.com/fnkr/inwxcli
Author: Florian Kaiser
Author-email: florian.kaiser@fnkr.net
License: MIT
Platform: UNKNOWN
